{"notionLogo":"./data/villarreal/teams-483-180.png","notionName":"比利亚雷亚尔","players":[{"left":"-1.18%","top":"0%","img":"./data/villarreal/players-236-276-22_180.png","href":"/player/236276/arnaut-danjuma/","defaultimg":"https://cdn.sofifa.net/players/notfound_0_60.png","name":"Danjuma","teamlogo":"./data/villarreal/flags-nl@3x.png"},{"left":"36%","top":"-2.5%","img":"./data/villarreal/players-208-093-22_180.png","href":"/player/208093/gerard-moreno-balaguero/","defaultimg":"https://cdn.sofifa.net/players/notfound_0_60.png","name":"Gerard Moreno","teamlogo":"./data/villarreal/flags-es@3x.png"},{"left":"74.06%","top":"0%","img":"./data/villarreal/players-246-172-22_180.png","href":"/player/246172/samuel-chukwueze/","defaultimg":"https://cdn.sofifa.net/players/notfound_0_60.png","name":"Chukwueze","teamlogo":"./data/villarreal/flags-ng@3x.png"},{"left":"20.16%","top":"33.75%","img":"./data/villarreal/players-226-226-22_180.png","href":"/player/226226/giovani-lo-celso/","defaultimg":"https://cdn.sofifa.net/players/notfound_0_60.png","name":"Lo Celso","teamlogo":"./data/villarreal/flags-ar@3x.png"},{"left":"51.84%","top":"33.75%","img":"./data/villarreal/players-189-513-22_180.png","href":"/player/189513/daniel-parejo-munoz/","defaultimg":"https://cdn.sofifa.net/players/notfound_0_60.png","name":"Parejo","teamlogo":"./data/villarreal/flags-es@3x.png"},{"left":"36%","top":"47.5%","img":"./data/villarreal/players-189-271-22_180.png","href":"/player/189271/francis-coquelin/","defaultimg":"https://cdn.sofifa.net/players/notfound_0_60.png","name":"Coquelin","teamlogo":"./data/villarreal/flags-fr@3x.png"},{"left":"-3.16%","top":"62.5%","img":"./data/villarreal/players-228-302-22_180.png","href":"/player/228302/alfonso-pedraza-sag/","defaultimg":"https://cdn.sofifa.net/players/notfound_0_60.png","name":"Pedraza","teamlogo":"./data/villarreal/flags-es@3x.png"},{"left":"20.16%","top":"70%","img":"./data/villarreal/players-241-464-22_180.png","href":"/player/241464/pau-francisco-torres/","defaultimg":"https://cdn.sofifa.net/players/notfound_0_60.png","name":"Pau Torres","teamlogo":"./data/villarreal/flags-es@3x.png"},{"left":"51.84%","top":"70%","img":"./data/villarreal/players-157-481-22_180.png","href":"/player/157481/raul-albiol-tortajada/","defaultimg":"https://cdn.sofifa.net/players/notfound_0_60.png","name":"Raúl Albiol","teamlogo":"./data/villarreal/flags-es@3x.png"},{"left":"75.16%","top":"62.5%","img":"./data/villarreal/players-237-221-22_180.png","href":"/player/237221/juan-foyth/","defaultimg":"https://cdn.sofifa.net/players/notfound_0_60.png","name":"Foyth","teamlogo":"./data/villarreal/flags-ar@3x.png"},{"left":"36%","top":"83.5%","img":"./data/villarreal/players-215-316-22_180.png","href":"/player/215316/geronimo-rulli/","defaultimg":"https://cdn.sofifa.net/players/notfound_0_60.png","name":"Rulli","teamlogo":"./data/villarreal/flags-ar@3x.png"}],"teamname":"villarreal"}