{"notionLogo":"./data/australia/teams-1415-180.png","notionName":"澳大利亚","players":[{"left":"35.956%","top":"0%","img":"./data/australia/players-212-232-23_180.png","href":"/player/212232/jamie-maclaren/","defaultimg":"https://cdn.sofifa.net/players/notfound_0_60.png","name":"Maclaren","teamlogo":"./data/australia/teams-81-180.png","pac":81,"sho":75,"pas":64,"dri":73,"def":39,"phy":76,"rating":"75","pos":"ST"},{"left":"9.6%","top":"18.75%","img":"./data/australia/players-195-033-23_180.png","href":"/player/195033/mathew-leckie/","defaultimg":"https://cdn.sofifa.net/players/notfound_0_60.png","name":"Leckie","teamlogo":"./data/australia/teams-112224-180.png","pac":82,"sho":65,"pas":64,"dri":72,"def":53,"phy":75,"rating":"71","pos":"LM"},{"left":"36%","top":"18.75%","img":"./data/australia/players-237-647-23_180.png","href":"/player/237647/ajdin-hrustic/","defaultimg":"https://cdn.sofifa.net/players/notfound_0_60.png","name":"Hrustić","teamlogo":"./data/australia/teams-206-180.png","pac":74,"sho":68,"pas":73,"dri":73,"def":60,"phy":70,"rating":"72","pos":"CM"},{"left":"62.4%","top":"18.75%","img":"./data/australia/players-211-221-23_180.png","href":"/player/211221/martin-boyle/","defaultimg":"https://cdn.sofifa.net/players/notfound_0_60.png","name":"Boyle","teamlogo":"./data/australia/teams-81-180.png","pac":92,"sho":69,"pas":62,"dri":72,"def":45,"phy":59,"rating":"72","pos":"RM"},{"left":"22.8%","top":"51.25%","img":"./data/australia/players-211-378-23_180.png","href":"/player/211378/jackson-irvine/","defaultimg":"https://cdn.sofifa.net/players/notfound_0_60.png","name":"Irvine","teamlogo":"./data/australia/teams-110329-180.png","pac":65,"sho":67,"pas":68,"dri":67,"def":67,"phy":76,"rating":"70","pos":"CM"},{"left":"48.32%","top":"47.5%","img":"./data/australia/players-194-958-23_180.png","href":"/player/194958/aaron-mooy/","defaultimg":"https://cdn.sofifa.net/players/notfound_0_60.png","name":"Mooy","teamlogo":"./data/australia/teams-78-180.png","pac":62,"sho":72,"pas":78,"dri":74,"def":69,"phy":75,"rating":"76","pos":"CM"},{"left":"-3.6%","top":"62.5%","img":"./data/australia/players-202-157-23_180.png","href":"/player/202157/aziz-behich/","defaultimg":"https://cdn.sofifa.net/players/notfound_0_60.png","name":"Behich","teamlogo":"./data/australia/teams-181-180.png","pac":77,"sho":63,"pas":64,"dri":71,"def":66,"phy":67,"rating":"70","pos":"LB"},{"left":"20.2304%","top":"67.5%","img":"./data/australia/players-229-585-23_180.png","href":"/player/229585/milos-degenek/","defaultimg":"https://cdn.sofifa.net/players/notfound_0_60.png","name":"Degenek","teamlogo":"./data/australia/teams-687-180.png","pac":76,"sho":61,"pas":66,"dri":60,"def":70,"phy":83,"rating":"72","pos":"CB"},{"left":"51.4968%","top":"67.5%","img":"./data/australia/players-199-000-23_180.png","href":"/player/199000/trent-sainsbury/","defaultimg":"https://cdn.sofifa.net/players/notfound_0_60.png","name":"Sainsbury","teamlogo":"./data/australia/teams-100081-180.png","pac":64,"sho":58,"pas":56,"dri":54,"def":74,"phy":75,"rating":"72","pos":"CB"},{"left":"75.6%","top":"62.5%","img":"./data/australia/players-243-473-23_180.png","href":"/player/243473/fran-karacic/","defaultimg":"https://cdn.sofifa.net/players/notfound_0_60.png","name":"Karačić","teamlogo":"./data/australia/teams-190-180.png","pac":81,"sho":46,"pas":62,"dri":66,"def":62,"phy":74,"rating":"69","pos":"RB"},{"left":"36%","top":"83.25%","img":"./data/australia/players-199-005-23_180.png","href":"/player/199005/mathew-ryan/","defaultimg":"https://cdn.sofifa.net/players/notfound_0_60.png","name":"Ryan","teamlogo":"./data/australia/teams-819-180.png","pac":78,"sho":76,"pas":82,"dri":80,"def":53,"phy":76,"rating":"78","pos":"GK"}],"teamname":"australia"}