{"notionLogo":"./data/werder/teams-38-180.png","notionName":"云达不莱梅","players":[{"left":"21.92%","top":"-14%","img":"./data/werder/players-205-431-22_180.png","href":"/player/11813973/niclas-fullkrug/","defaultimg":"https://cdn.sofifa.net/players/notfound_0_60.png","name":"Füllkrug","teamlogo":"./data/werder/flags-de@3x.png"},{"left":"47.44%","top":"-11%","img":"./data/werder/players-197-031-22_180.png","href":"/player/11813979/marvin-ducksch/","defaultimg":"https://cdn.sofifa.net/players/notfound_0_60.png","name":"Ducksch","teamlogo":"./data/werder/flags-de@3x.png"},{"left":"20.16%","top":"30%","img":"./data/werder/players-203-106-22_180.png","href":"/player/11813958/leonardo-bittencourt/","defaultimg":"https://cdn.sofifa.net/players/notfound_0_60.png","name":"Bittencourt","teamlogo":"./data/werder/flags-de@3x.png"},{"left":"33.36%","top":"33%","img":"./data/werder/players-248-384-22_180.png","href":"/player/11813994/ilia-gruev/","defaultimg":"https://cdn.sofifa.net/players/notfound_0_60.png","name":"Gruev","teamlogo":"./data/werder/flags-bg@3x.png"},{"left":"51.84%","top":"30%","img":"./data/werder/players-232-711-22_180.png","href":"/player/12129294/jens-stage/","defaultimg":"https://cdn.sofifa.net/players/notfound_0_60.png","name":"Stage","teamlogo":"./data/werder/flags-dk@3x.png"},{"left":"1.68%","top":"37%","img":"./data/werder/players-207-897-22_180.png","href":"/player/11813996/anthony-jung/","defaultimg":"https://cdn.sofifa.net/players/notfound_0_60.png","name":"Jung","teamlogo":"./data/werder/flags-de@3x.png"},{"left":"12.24%","top":"62%","img":"./data/werder/players-237-595-22_180.png","href":"/player/11813955/marco-friedl/","defaultimg":"https://cdn.sofifa.net/players/notfound_0_60.png","name":"Friedl","teamlogo":"./data/werder/flags-at@3x.png"},{"left":"36%","top":"62.5%","img":"./data/werder/players-221-354-22_180.png","href":"/player/11813944/milos-veljkovic/","defaultimg":"https://cdn.sofifa.net/players/notfound_0_60.png","name":"Veljković","teamlogo":"./data/werder/flags-rs@3x.png"},{"left":"53.6%","top":"62%","img":"./data/werder/players-246-836-22_180.png","href":"/player/12129285/amos-pieper/","defaultimg":"https://cdn.sofifa.net/players/notfound_0_60.png","name":"Pieper","teamlogo":"./data/werder/flags-de@3x.png"},{"left":"65.04%","top":"41%","img":"./data/werder/players-206-591-22_180.png","href":"/player/11813943/mitchell-weiser/","defaultimg":"https://cdn.sofifa.net/players/notfound_0_60.png","name":"Weiser","teamlogo":"./data/werder/flags-de@3x.png"},{"left":"36%","top":"83.5%","img":"./data/werder/players-236-583-22_180.png","href":"/player/11813933/jiri-pavlenka/","defaultimg":"https://cdn.sofifa.net/players/notfound_0_60.png","name":"Pavlenka","teamlogo":"./data/werder/flags-cz@3x.png"}],"teamname":"werder"}