{"notionLogo":"./data/sheffield/teams-1794-180.png","notionName":"谢菲尔德联","players":[{"left":"36%","top":"-2.5%","img":"./data/sheffield/players-163-050-22_180.png","href":"/player/163050/billy-sharp/","defaultimg":"https://cdn.sofifa.net/players/notfound_0_60.png","name":"Sharp","teamlogo":"./data/sheffield/flags-gb-eng@3x.png"},{"left":"0.8%","top":"20%","img":"./data/sheffield/players-210-985-22_180.png","href":"/player/210985/ben-osborn/","defaultimg":"https://cdn.sofifa.net/players/notfound_0_60.png","name":"Osborn","teamlogo":"./data/sheffield/flags-gb-eng@3x.png"},{"left":"20.16%","top":"33.75%","img":"./data/sheffield/players-189-177-22_180.png","href":"/player/189177/john-fleck/","defaultimg":"https://cdn.sofifa.net/players/notfound_0_60.png","name":"Fleck","teamlogo":"./data/sheffield/flags-gb-sct@3x.png"},{"left":"36%","top":"42%","img":"./data/sheffield/players-228-092-22_180.png","href":"/player/228092/sander-berge/","defaultimg":"https://cdn.sofifa.net/players/notfound_0_60.png","name":"Berge","teamlogo":"./data/sheffield/flags-no@3x.png"},{"left":"51.84%","top":"33.75%","img":"./data/sheffield/players-186-143-22_180.png","href":"/player/186143/oliver-norwood/","defaultimg":"https://cdn.sofifa.net/players/notfound_0_60.png","name":"Norwood","teamlogo":"./data/sheffield/flags-gb-nir@3x.png"},{"left":"71.2%","top":"20%","img":"./data/sheffield/players-244-591-22_180.png","href":"/player/244591/jayden-bogle/","defaultimg":"https://cdn.sofifa.net/players/notfound_0_60.png","name":"Bogle","teamlogo":"./data/sheffield/flags-gb-eng@3x.png"},{"left":"-3.16%","top":"62.5%","img":"./data/sheffield/players-212-100-22_180.png","href":"/player/212100/max-lowe/","defaultimg":"https://cdn.sofifa.net/players/notfound_0_60.png","name":"Lowe","teamlogo":"./data/sheffield/flags-gb-eng@3x.png"},{"left":"20.16%","top":"70%","img":"./data/sheffield/players-204-936-22_180.png","href":"/player/204936/john-egan/","defaultimg":"https://cdn.sofifa.net/players/notfound_0_60.png","name":"Egan","teamlogo":"./data/sheffield/flags-ie@3x.png"},{"left":"47.44%","top":"59%","img":"./data/sheffield/players-212-300-22_180.png","href":"/player/212300/jack-oconnell/","defaultimg":"https://cdn.sofifa.net/players/notfound_0_60.png","name":"O'Connell","teamlogo":"./data/sheffield/flags-gb-eng@3x.png"},{"left":"75.16%","top":"62.5%","img":"./data/sheffield/players-200-855-22_180.png","href":"/player/200855/george-baldock/","defaultimg":"https://cdn.sofifa.net/players/notfound_0_60.png","name":"Baldock","teamlogo":"./data/sheffield/flags-gb-eng@3x.png"},{"left":"36%","top":"83.5%","img":"./data/sheffield/players-193-182-22_180.png","href":"/player/193182/wes-foderingham/","defaultimg":"https://cdn.sofifa.net/players/notfound_0_60.png","name":"Foderingham","teamlogo":"./data/sheffield/flags-gb-eng@3x.png"}],"teamname":"sheffield"}